synpla_datetimepicker-0.1.4.dist-info/RECORD
synpla_datetimepicker-0.1.4.dist-info/DESCRIPTION.rst
synpla_datetimepicker-0.1.4.dist-info/top_level.txt
synpla_datetimepicker-0.1.4.dist-info/METADATA
synpla_datetimepicker-0.1.4.dist-info/WHEEL
synpla_datetimepicker-0.1.4.dist-info/metadata.json
synpla_datetimepicker/__init__.py
synpla_datetimepicker/static/css/libs/bootstrap-datetimepicker.min.css
synpla_datetimepicker/static/js/app-datetimepicker.js
synpla_datetimepicker/static/js/libs/bootstrap-datetimepicker.js
synpla_datetimepicker/templates/datetimepicker/macros/datetimepicker.html
